LICENSE
lucius_ltv/__init__.py
lucius_ltv/model.py
lucius_ltv/plots.py
lucius_ltv/utils.py
lucius_ltv-0.2.0.dist-info/LICENSE
lucius_ltv-0.2.0.dist-info/WHEEL
lucius_ltv-0.2.0.dist-info/METADATA
lucius_ltv-0.2.0.dist-info/RECORD
