Metadata-Version: 2.1
Name: lucius-ltv
Version: 0.2.0
Summary: A simple multicohort LTV calculator for subscription based products
Home-page: https://github.com/plexagon/lucius-ltv
License: MIT
Keywords: ltv,lifetime,value,cltv
Author: Luca Giacomel
Author-email: luca.giacomel@gmail.com
Requires-Python: >=3.9,<4.0
Classifier: License :: OSI Approved :: MIT License
Classifier: Programming Language :: Python :: 3
Classifier: Programming Language :: Python :: 3.9
Classifier: Programming Language :: Python :: 3.10
Classifier: Programming Language :: Python :: 3.11
Requires-Dist: arviz (>=0.13.0)
Requires-Dist: pymc (>=5.1.0)
Requires-Dist: pytensor (>=2.10.1,<3.0.0)
Requires-Dist: seaborn (>=0.11.2,<0.12.0)
Project-URL: Repository, https://github.com/plexagon/lucius-ltv
